markdown_extensions/__init__.py
markdown_extensions/checklist/__init__.py
markdown_extensions/checklist/extension.py
markdown_extensions/emoji/__init__.py
markdown_extensions/emoji/extension.py
markdown_extensions-0.0.1.dist-info/LICENSE
markdown_extensions-0.0.1.dist-info/METADATA
markdown_extensions-0.0.1.dist-info/WHEEL
markdown_extensions-0.0.1.dist-info/top_level.txt
markdown_extensions-0.0.1.dist-info/RECORD
